wrapconfig/__init__.py
wrapconfig/_read.py
wrapconfig/core.py
wrapconfig/inmemory.py
wrapconfig/jsonconfig.py
wrapconfig/tomlconfig.py
wrapconfig/yamlconf.py
WrapConfig-0.2.2.dist-info/LICENSE
WrapConfig-0.2.2.dist-info/METADATA
WrapConfig-0.2.2.dist-info/WHEEL
WrapConfig-0.2.2.dist-info/top_level.txt
WrapConfig-0.2.2.dist-info/RECORD
