Metadata-Version: 2.2
Name: WrapConfig
Version: 0.2.2
Summary: Wraper to manage configurations
Author-email: Julian Kimmig <julian.kimmig@linkdlab.de>
License: MIT
Project-URL: homepage, https://github.com/JulianKimmig/WrapConfig
Project-URL: source, https://github.com/JulianKimmig/WrapConfig
Project-URL: tracker, https://github.com/JulianKimmig/WrapConfig/issues
Requires-Python: >=3.10
License-File: LICENSE
Provides-Extra: toml
Requires-Dist: toml>=0.10.2; extra == "toml"
Provides-Extra: yaml
Requires-Dist: pyyaml>=6.0.2; extra == "yaml"
Provides-Extra: all
Requires-Dist: toml>=0.10.2; extra == "all"
Requires-Dist: pyyaml>=6.0.2; extra == "all"
